aiopolymarket/__init__.py
aiopolymarket/client.py
aiopolymarket/data_client.py
aiopolymarket/enums.py
aiopolymarket/exceptions.py
aiopolymarket/models.py
aiopolymarket-0.0.1.dist-info/METADATA
aiopolymarket-0.0.1.dist-info/WHEEL
aiopolymarket-0.0.1.dist-info/top_level.txt
aiopolymarket-0.0.1.dist-info/RECORD
