Metadata-Version: 2.4
Name: aiopolymarket
Version: 0.0.1
Summary: A comprehensive, type-safe async Python client for Polymarket.
Requires-Python: >=3.12
Requires-Dist: aiohttp>=3.13.0
Requires-Dist: pydantic>=2.12.0
